findprob/__about__.py
findprob/__init__.py
findprob/__main__.py
findprob/classify_helpers.py
findprob/cli.py
findprob/findprob.py
findprob/text_helpers.py
findprob-0.2.dist-info/METADATA
findprob-0.2.dist-info/WHEEL
findprob-0.2.dist-info/entry_points.txt
findprob-0.2.dist-info/licenses/LICENSE
findprob-0.2.dist-info/RECORD
