Metadata-Version: 2.4
Name: findprob
Version: 0.2
Summary: A CLI that lets you classify and search for problems by topic using an LLM
Project-URL: Homepage, https://phrdang.github.io/findprob/
Project-URL: Repository, https://github.com/phrdang/findprob.git
Project-URL: Issues, https://github.com/phrdang/findprob/issues
Author-email: Rebecca Dang <rdang@berkeley.edu>, Jessica Lin <linjessica@berkeley.edu>, Samantha Huang <samanthahuang@berkeley.edu>
Maintainer-email: Rebecca Dang <rdang@berkeley.edu>, Jessica Lin <linjessica@berkeley.edu>, Samantha Huang <samanthahuang@berkeley.edu>
License-File: LICENSE
Keywords: AI,LLM,classify problems,edtech,education,find problems,findprob,problems,search problems
Classifier: Development Status :: 1 - Planning
Classifier: License :: OSI Approved :: MIT License
Classifier: Programming Language :: Python :: 3.11
Classifier: Topic :: Education
Classifier: Topic :: Scientific/Engineering :: Artificial Intelligence
Requires-Python: >=3.11
Requires-Dist: beautifulsoup4
Requires-Dist: faiss-cpu
Requires-Dist: langchain
Requires-Dist: langchain-community
Requires-Dist: langchain-core
Requires-Dist: langchain-openai
Requires-Dist: lxml
Requires-Dist: pypdf
Requires-Dist: typer>=0.12.3
